aiosqlembic/__init__.py
aiosqlembic/main.py
aiosqlembic/models/__init__.py
aiosqlembic/models/cli.py
aiosqlembic/models/inspector.py
aiosqlembic/schema.py
aiosqlembic/sql/aiosqlembic/aiosqlite/checks.sql
aiosqlembic/sql/aiosqlembic/aiosqlite/migrations.sql
aiosqlembic/sql/aiosqlembic/asyncpg/checks.sql
aiosqlembic/sql/aiosqlembic/asyncpg/migrations.sql
aiosqlembic/sql/metadata/all_relations.sql
aiosqlembic/sql/metadata/collations.sql
aiosqlembic/sql/metadata/constraints.sql
aiosqlembic/sql/metadata/deps.sql
aiosqlembic/sql/metadata/domains.sql
aiosqlembic/sql/metadata/enum.sql
aiosqlembic/sql/metadata/extensions.sql
aiosqlembic/sql/metadata/functions.sql
aiosqlembic/sql/metadata/indexes.sql
aiosqlembic/sql/metadata/privileges.sql
aiosqlembic/sql/metadata/rlspolicies.sql
aiosqlembic/sql/metadata/schema.sql
aiosqlembic/sql/metadata/sequences.sql
aiosqlembic/sql/metadata/triggers.sql
aiosqlembic/sql/metadata/types.sql
aiosqlembic/templates/revision.sql
aiosqlembic/utils.py
aiosqlembic-0.3.12.dist-info/entry_points.txt
aiosqlembic-0.3.12.dist-info/LICENSE
aiosqlembic-0.3.12.dist-info/WHEEL
aiosqlembic-0.3.12.dist-info/METADATA
aiosqlembic-0.3.12.dist-info/RECORD
